scraping_toolbox/__init__.py
scraping_toolbox-0.0.1.dist-info/METADATA
scraping_toolbox-0.0.1.dist-info/WHEEL
scraping_toolbox-0.0.1.dist-info/top_level.txt
scraping_toolbox-0.0.1.dist-info/RECORD
