Metadata-Version: 2.1
Name: scraping-toolbox
Version: 0.0.1
Summary: This is ment to be a helper repo for diferent scraping projects 
Home-page: https://github.com/Liitle/scraping_toolbox
Author: George Dragan
Author-email: 
Maintainer: George Dragan
Maintainer-email: 
License: MIT license
Keywords: scraping_toolbox
Platform: UNKNOWN
Classifier: Development Status :: 3 - Alpha
Classifier: Intended Audience :: Developers
Classifier: Programming Language :: Python :: 3.7
